awesome_panel_cli/__init__.py
awesome_panel_cli/config.py
awesome_panel_cli/hello.py
awesome_panel_cli/shared.py
awesome_panel_cli/cli/__init__.py
awesome_panel_cli/cli/autoformat.py
awesome_panel_cli/cli/build.py
awesome_panel_cli/cli/create.py
awesome_panel_cli/cli/main.py
awesome_panel_cli/cli/release.py
awesome_panel_cli/cli/test.py
awesome_panel_cli/templates/.binder/postBuild
awesome_panel_cli/templates/.binder/requirements.txt
awesome_panel_cli/templates/.binder/start
awesome_panel_cli/templates/.github/ISSUE_TEMPLATE/bug_report.yml
awesome_panel_cli/templates/.github/ISSUE_TEMPLATE/config.yml
awesome_panel_cli/templates/.github/ISSUE_TEMPLATE/feature_request.yml
awesome_panel_cli/templates/.github/workflows/tests.yaml
awesome_panel_cli/templates/apps/altair_starter.py
awesome_panel_cli/templates/apps/cross_filtering.py
awesome_panel_cli/templates/apps/hello_world.py
awesome_panel_cli/templates/apps/streaming_indicators.py
awesome_panel_cli/templates/assets/videos/pn-hello-{{ cookiecutter.project_slug }}.gif
awesome_panel_cli/templates/licenses/mit
awesome_panel_cli/templates/notebooks/getting_started.ipynb
awesome_panel_cli/templates/notebooks/introduction.ipynb
awesome_panel_cli/templates/project/cookiecutter.json
awesome_panel_cli/templates/project/{{cookiecutter.project_slug}}/.gitattributes
awesome_panel_cli/templates/project/{{cookiecutter.project_slug}}/.gitignore
awesome_panel_cli/templates/project/{{cookiecutter.project_slug}}/DEVELOPER_GUIDE.md
awesome_panel_cli/templates/project/{{cookiecutter.project_slug}}/MANIFEST.in
awesome_panel_cli/templates/project/{{cookiecutter.project_slug}}/README.md
awesome_panel_cli/templates/project/{{cookiecutter.project_slug}}/code-of-conduct.md
awesome_panel_cli/templates/project/{{cookiecutter.project_slug}}/pyproject.toml
awesome_panel_cli/templates/project/{{cookiecutter.project_slug}}/apps/app.py
awesome_panel_cli/templates/project/{{cookiecutter.project_slug}}/src/{{cookiecutter.package_slug}}/__init__.py
awesome_panel_cli-0.1.0rc11.dist-info/LICENSE
awesome_panel_cli-0.1.0rc11.dist-info/METADATA
awesome_panel_cli-0.1.0rc11.dist-info/WHEEL
awesome_panel_cli-0.1.0rc11.dist-info/entry_points.txt
awesome_panel_cli-0.1.0rc11.dist-info/top_level.txt
awesome_panel_cli-0.1.0rc11.dist-info/RECORD
