Metadata-Version: 2.1
Name: awesome-panel-cli
Version: 0.1.0rc11
Summary: A CLI tool to speed up your workflow when developing Panel applications
Author: awesome-panel
License: MIT License        
Project-URL: repository, https://github.com/awesome-panel/awesome-panel-cli
Keywords: python,holoviz,panel,cli,dataviz,dataapp,dashboard,datascience,analytics
Classifier: License :: OSI Approved :: MIT License
Classifier: Development Status :: 3 - Alpha
Classifier: Programming Language :: Python :: 3
Classifier: Programming Language :: Python :: 3.7
Classifier: Programming Language :: Python :: 3.8
Classifier: Programming Language :: Python :: 3.9
Classifier: Programming Language :: Python :: 3.10
Classifier: Operating System :: OS Independent
Classifier: Intended Audience :: Developers
Classifier: Intended Audience :: Education
Classifier: Intended Audience :: Financial and Insurance Industry
Classifier: Intended Audience :: Healthcare Industry
Classifier: Intended Audience :: Information Technology
Classifier: Intended Audience :: Legal Industry
Classifier: Intended Audience :: Other Audience
Classifier: Intended Audience :: Science/Research
Classifier: Natural Language :: English
Classifier: Topic :: Office/Business :: Financial
Classifier: Topic :: Office/Business
Classifier: Topic :: Scientific/Engineering :: Information Analysis
Classifier: Topic :: Scientific/Engineering :: Visualization
Classifier: Topic :: Scientific/Engineering
Classifier: Topic :: Software Development :: Libraries
Requires-Python: >=3.7
License-File: LICENSE
Requires-Dist: cookiecutter
Requires-Dist: gitdir
Requires-Dist: rich
Requires-Dist: typer
Requires-Dist: Markdown (>=3.4.1)
Provides-Extra: all
Requires-Dist: autoflake ; extra == 'all'
Requires-Dist: bandit ; extra == 'all'
Requires-Dist: black[jupyter] ; extra == 'all'
Requires-Dist: build ; extra == 'all'
Requires-Dist: mypy ; extra == 'all'
Requires-Dist: pylint ; extra == 'all'
Requires-Dist: pylint2junit ; extra == 'all'
Requires-Dist: pytest-cov ; extra == 'all'
Requires-Dist: pytest-mock ; extra == 'all'
Requires-Dist: pytest ; extra == 'all'
Requires-Dist: toml ; extra == 'all'
Requires-Dist: twine ; extra == 'all'
Requires-Dist: typer[all] ; extra == 'all'
Requires-Dist: types-invoke ; extra == 'all'
Requires-Dist: types-requests ; extra == 'all'
Requires-Dist: types-setuptools ; extra == 'all'
Requires-Dist: wheel ; extra == 'all'
Requires-Dist: altair ; extra == 'all'
Requires-Dist: hvplot ; extra == 'all'
Requires-Dist: matplotlib ; extra == 'all'
Requires-Dist: notebook ; extra == 'all'
Requires-Dist: pandas ; extra == 'all'
Requires-Dist: panel ; extra == 'all'
Requires-Dist: vega-datasets ; extra == 'all'
Provides-Extra: dev
Requires-Dist: autoflake ; extra == 'dev'
Requires-Dist: bandit ; extra == 'dev'
Requires-Dist: black[jupyter] ; extra == 'dev'
Requires-Dist: build ; extra == 'dev'
Requires-Dist: mypy ; extra == 'dev'
Requires-Dist: pylint ; extra == 'dev'
Requires-Dist: pylint2junit ; extra == 'dev'
Requires-Dist: pytest-cov ; extra == 'dev'
Requires-Dist: pytest-mock ; extra == 'dev'
Requires-Dist: pytest ; extra == 'dev'
Requires-Dist: toml ; extra == 'dev'
Requires-Dist: twine ; extra == 'dev'
Requires-Dist: typer[all] ; extra == 'dev'
Requires-Dist: typer-cli ; extra == 'dev'
Requires-Dist: types-invoke ; extra == 'dev'
Requires-Dist: types-requests ; extra == 'dev'
Requires-Dist: types-setuptools ; extra == 'dev'
Requires-Dist: wheel ; extra == 'dev'
Provides-Extra: examples
Requires-Dist: altair ; extra == 'examples'
Requires-Dist: hvplot ; extra == 'examples'
Requires-Dist: matplotlib ; extra == 'examples'
Requires-Dist: notebook ; extra == 'examples'
Requires-Dist: pandas ; extra == 'examples'
Requires-Dist: panel ; extra == 'examples'
Requires-Dist: vega-datasets ; extra == 'examples'
